opof/__init__.py
opof/algorithm.py
opof/domain.py
opof/evaluator.py
opof/generator.py
opof/parameter_space.py
opof/planner.py
opof/problem_set.py
opof/py.typed
opof/algorithms/__init__.py
opof/algorithms/gc.py
opof/algorithms/pypop.py
opof/algorithms/smac.py
opof/evaluators/__init__.py
opof/evaluators/list_evaluator.py
opof/models/__init__.py
opof/models/fc_resnet.py
opof/models/static.py
opof/parameter_spaces/__init__.py
opof/parameter_spaces/interval.py
opof/parameter_spaces/power_spherical.py
opof/parameter_spaces/simplex.py
opof/parameter_spaces/sphere.py
opof/problem_sets/__init__.py
opof/problem_sets/problem_list.py
opof/registry/__init__.py
opof/registry/utils.py
opof-0.3.1.data/scripts/opof-registry
opof-0.3.1.data/scripts/opof-train
opof-0.3.1.dist-info/LICENSE.md
opof-0.3.1.dist-info/METADATA
opof-0.3.1.dist-info/WHEEL
opof-0.3.1.dist-info/top_level.txt
opof-0.3.1.dist-info/RECORD
