Metadata-Version: 2.1
Name: opof
Version: 0.3.1
Summary: Open-source framework for solving the Planner Optimization Problem
Home-page: https://opof.kavrakilab.org
Author: Yiyuan Lee
Author-email: yiyuan.lee@rice.edu
License: BSD-3
Project-URL: Documentation, https://opof.kavrakilab.org
Project-URL: Source, https://github.com/opoframework/opof
Keywords: opof,optimization,machine learning,reinforcement learning,planning,robotics
Classifier: Development Status :: 4 - Beta
Classifier: Intended Audience :: Developers
Classifier: Intended Audience :: Education
Classifier: Intended Audience :: Science/Research
Classifier: Topic :: Scientific/Engineering
Classifier: Topic :: Scientific/Engineering :: Mathematics
Classifier: Topic :: Scientific/Engineering :: Artificial Intelligence
Classifier: Topic :: Software Development
Classifier: Topic :: Software Development :: Libraries
Classifier: Topic :: Software Development :: Libraries :: Python Modules
Classifier: License :: OSI Approved :: BSD License
Classifier: Programming Language :: Python :: 3.9
Classifier: Programming Language :: Python :: 3.10
Requires-Python: >=3.9
License-File: LICENSE.md
Requires-Dist: torch
Requires-Dist: tqdm
Requires-Dist: pyyaml
Requires-Dist: swig
Requires-Dist: smac (==2.0.0)
Requires-Dist: pypop7
Requires-Dist: scikit-learn (==1.2.0)
Requires-Dist: tensorboard
Provides-Extra: tests
Requires-Dist: pytest ; extra == 'tests'
Requires-Dist: pytest-cov ; extra == 'tests'
